pekutko_serializer/__init__.py
pekutko_serializer-0.0.3.dist-info/METADATA
pekutko_serializer-0.0.3.dist-info/WHEEL
pekutko_serializer-0.0.3.dist-info/top_level.txt
pekutko_serializer-0.0.3.dist-info/RECORD
