Metadata-Version: 2.1
Name: pekutko-serializer
Version: 0.0.3
Summary: Dmitry Pekutko, gruop 053504, format cenverter (Serializer)
Home-page: https://github.com/DimaPekutko/ISP-2022-053504/
Author: Dmitry Pekutko
Author-email: dkefir03@gmail.com
License: UNKNOWN
Platform: UNKNOWN
